stock_data_package/__init__.py
stock_data_package/stock_data.py
stock_data_package-0.1.dist-info/LICENSE.txt
stock_data_package-0.1.dist-info/METADATA
stock_data_package-0.1.dist-info/WHEEL
stock_data_package-0.1.dist-info/top_level.txt
stock_data_package-0.1.dist-info/RECORD
